core/middleware.py
apilimity-0.1.0.dist-info/METADATA
apilimity-0.1.0.dist-info/WHEEL
apilimity-0.1.0.dist-info/top_level.txt
apilimity-0.1.0.dist-info/RECORD
