Metadata-Version: 2.4
Name: apilimity
Version: 0.1.0
Summary: APIlimity – FastAPI-based request limiter and API key manager
Author-email: Oleksii Valitov <valitovalexey@gmail.com>
License: MIT
Project-URL: Homepage, https://github.com/shtilev/apilimity
Project-URL: Documentation, https://github.com/shtilev/apilimity
Project-URL: Source, https://github.com/shtilev/apilimity
Project-URL: Issues, https://github.com/shtilev/apilimity/issues
Requires-Dist: fastapi>=0.109.0
Requires-Dist: uvicorn[standard]>=0.27.0
Requires-Dist: redis>=5.0.1
